pyconfig/__init__.py
pyconfig/clean.py
pyconfig/config_exceptions.py
pyconfig/parse.py
pyconfig_env-1.0.0.dist-info/LICENSE
pyconfig_env-1.0.0.dist-info/METADATA
pyconfig_env-1.0.0.dist-info/WHEEL
pyconfig_env-1.0.0.dist-info/top_level.txt
pyconfig_env-1.0.0.dist-info/RECORD
