Metadata-Version: 2.1
Name: pyconfig-env
Version: 1.0.0
Summary: Automatic Python Environment Variable Configuration
Home-page: https://github.com/computer-geek64/pyconfig
Author: Ashish D'Souza
Author-email: sudouser512@gmail.com
License: UNKNOWN
Platform: UNKNOWN
Classifier: Programming Language :: Python :: 3
Classifier: License :: OSI Approved :: MIT License
Classifier: Operating System :: OS Independent
Requires-Python: >=3.6
